yomitoku_client/__init__.py
yomitoku_client/client.py
yomitoku_client/constants.py
yomitoku_client/exceptions.py
yomitoku_client/font_manager.py
yomitoku_client/logger.py
yomitoku_client/models.py
yomitoku_client/parser.py
yomitoku_client/utils.py
yomitoku_client/cli/__init__.py
yomitoku_client/cli/batch.py
yomitoku_client/cli/cli.py
yomitoku_client/cli/single.py
yomitoku_client/cli/utils.py
yomitoku_client/renderers/__init__.py
yomitoku_client/renderers/base.py
yomitoku_client/renderers/csv_renderer.py
yomitoku_client/renderers/factory.py
yomitoku_client/renderers/html_renderer.py
yomitoku_client/renderers/json_renderer.py
yomitoku_client/renderers/markdown_renderer.py
yomitoku_client/renderers/pdf_renderer.py
yomitoku_client/renderers/searchable_pdf.py
yomitoku_client/resource/MPLUS1p-Medium.ttf
yomitoku_client/resource/charset.txt
yomitoku_client/visualizers/__init__.py
yomitoku_client/visualizers/base.py
yomitoku_client/visualizers/document_visualizer.py
yomitoku_client-0.1.1.dist-info/METADATA
yomitoku_client-0.1.1.dist-info/WHEEL
yomitoku_client-0.1.1.dist-info/entry_points.txt
yomitoku_client-0.1.1.dist-info/licenses/LICENSE
yomitoku_client-0.1.1.dist-info/RECORD
