Metadata-Version: 2.4
Name: yomitoku-client
Version: 0.1.1
Summary: YomiToku-Client is a Python library for processing SageMaker YomiToku API outputs with format conversion and visualization capabilities.
Project-URL: Homepage, https://github.com/MLism-Inc/yomitoku-client
Project-URL: Repository, https://github.com/MLism-Inc/yomitoku-client
Project-URL: Issues, https://github.com/MLism-Inc/yomitoku-client/issues
Author-email: "MLism Inc." <support-aws-marketplace@mlism.com>
License-Expression: Apache-2.0
License-File: LICENSE
Keywords: document-analysis,format-conversion,sagemaker,visualization,yomitoku
Requires-Python: <3.13,>=3.10
Requires-Dist: boto3>=1.26.0
Requires-Dist: click>=8.1.0
Requires-Dist: jaconv>=0.4.0
Requires-Dist: lxml>=5.3.0
Requires-Dist: numpy>=1.26.0
Requires-Dist: opencv-python>=4.8.0
Requires-Dist: pandas>=2.1.0
Requires-Dist: pillow>=9.5.0
Requires-Dist: pydantic>=2.9.2
Requires-Dist: pypdf2>=3.0.0
Requires-Dist: pypdfium2==4.30.0
Requires-Dist: reportlab>=4.4.1
Requires-Dist: requests>=2.28.0
